{
  "schemaVersion": "1.0.0",
  "id": "node-b007f638",
  "kind": "component",
  "source": {
    "componentId": "3827:150894",
    "nodeId": "3827:151160/3827:150905",
    "nodeType": "INSTANCE"
  },
  "propsSchema": {},
  "structure": {
    "nodeType": "INSTANCE",
    "name": "文本提示",
    "styleRefs": [],
    "ext": {
      "layoutStyle": {
        "width": 234,
        "height": 22,
        "relativeX": 314,
        "relativeY": 4
      },
      "flexContainerInfo": {
        "flexDirection": "row",
        "alignItems": "center",
        "mainSizing": "auto",
        "crossSizing": "auto",
        "gap": "4px"
      },
      "borderRadius": null,
      "textAlign": null,
      "textMode": null
    },
    "children": [
      {
        "nodeType": "TEXT",
        "name": "点击作品下方",
        "styleRefs": [
          "{textStyle.c-14px}",
          "{color.ty-50-box-hover}"
        ],
        "ext": {
          "layoutStyle": {
            "width": 84,
            "height": 22,
            "relativeX": 0,
            "relativeY": 0
          },
          "flexContainerInfo": null,
          "borderRadius": null,
          "textAlign": "left",
          "textMode": "single-line"
        },
        "text": [
          {
            "text": "点击作品下方",
            "font": "font_8:1425"
          }
        ]
      },
      {
        "nodeType": "COMPONENT_REF",
        "name": "属性 1[a2]=nor",
        "ref": "1-a2-nor-2b681135",
        "styleRefs": [],
        "ext": {
          "layoutStyle": {
            "width": 16,
            "height": 16,
            "relativeX": 88,
            "relativeY": 3
          },
          "flexContainerInfo": null,
          "borderRadius": null,
          "textAlign": null,
          "textMode": null
        }
      },
      {
        "nodeType": "TEXT",
        "name": "按钮，可设置代表作",
        "styleRefs": [
          "{textStyle.c-14px}",
          "{color.ty-50-box-hover}"
        ],
        "ext": {
          "layoutStyle": {
            "width": 126,
            "height": 22,
            "relativeX": 108,
            "relativeY": 0
          },
          "flexContainerInfo": null,
          "borderRadius": null,
          "textAlign": "left",
          "textMode": "single-line"
        },
        "text": [
          {
            "text": "按钮，可设置代表作",
            "font": "font_8:1425"
          }
        ]
      }
    ]
  }
}
